bioc/__init__.py
bioc/biocitertools.py
bioc/constants.py
bioc/datastructure.py
bioc/utils.py
bioc/validator.py
bioc/biocjson/__init__.py
bioc/biocjson/decoder.py
bioc/biocjson/encoder.py
bioc/biocxml/__init__.py
bioc/biocxml/decoder.py
bioc/biocxml/encoder.py
bioc/brat/__init__.py
bioc/brat/datastructure.py
bioc/brat/decoder.py
bioc/brat/encoder.py
bioc/brat/validator.py
bioc/cli/__init__.py
bioc/cli/brat2bioc.py
bioc/cli/split_bioc.py
bioc/pubtator/__init__.py
bioc/pubtator/datastructure.py
bioc/pubtator/decoder.py
bioc/pubtator/encoder.py
bioc/pubtator/validator.py
bioc/tools/__init__.py
bioc/tools/brat2bioc.py
bioc/tools/pubtator2bioc.py
bioc/tools/split.py
bioc-2.1.dist-info/LICENSE
bioc-2.1.dist-info/METADATA
bioc-2.1.dist-info/WHEEL
bioc-2.1.dist-info/entry_points.txt
bioc-2.1.dist-info/top_level.txt
bioc-2.1.dist-info/RECORD
