Metadata-Version: 2.1
Name: bioc
Version: 2.1
Summary: bioc - Processing BioC, Brat, and PubTator with Python.
Author-email: Yifan Peng <yip4002@med.cornell.edu>
Project-URL: Homepage, https://github.com/bionlplab/bioc
Keywords: bioc,brat,pubtator
Classifier: Development Status :: 1 - Planning
Classifier: Intended Audience :: Developers
Classifier: Intended Audience :: Science/Research
Classifier: License :: OSI Approved :: MIT License
Classifier: Operating System :: OS Independent
Classifier: Topic :: Text Processing :: Markup :: XML
Classifier: Topic :: Software Development :: Libraries :: Application Frameworks
Classifier: Programming Language :: Python :: 3
Requires-Python: >=3.6
License-File: LICENSE
